COPYING
LICENSE
README
setup.py
CleverHarold.egg-info/PKG-INFO
CleverHarold.egg-info/SOURCES.txt
CleverHarold.egg-info/dependency_links.txt
CleverHarold.egg-info/entry_points.txt
CleverHarold.egg-info/not-zip-safe
CleverHarold.egg-info/requires.txt
CleverHarold.egg-info/top_level.txt
docs/additional_middleware.txt
docs/caching.txt
docs/command_reference.txt
docs/databases.txt
docs/description.txt
docs/forms.txt
docs/installation.txt
docs/introduction.txt
docs/programs.txt
docs/session.txt
docs/templates.txt
docs/tutorial.txt
ez_setup/README.txt
ez_setup/__init__.py
harold/__init__.py
harold/armor/__init__.py
harold/armor/basetypes.py
harold/armor/validatorexc.py
harold/armor/validatorlib.py
harold/cache/__init__.py
harold/cache/decorators.py
harold/cache/langoliers.py
harold/cache/lib.py
harold/cache/middleware.py
harold/cache/storage.py
harold/database/__init__.py
harold/database/middleware.py
harold/form/__init__.py
harold/form/constructor/__init__.py
harold/form/responder/__init__.py
harold/form/responder/formexc.py
harold/form/responder/jsonexc.py
harold/lib/__init__.py
harold/lib/configparser.py
harold/lib/debug.py
harold/lib/errordoc.py
harold/lib/mppaste.py
harold/lib/mpwsgi.py
harold/log/__init__.py
harold/log/middleware.py
harold/plugins/__init__.py
harold/plugins/createproject.py
harold/plugins/factory.py
harold/plugins/lib.py
harold/plugins/modelshell.py
harold/plugins/recreatemodel.py
harold/plugins/serve.py
harold/plugins/showproject.py
harold/project/+package+.ini_tmpl
harold/project/setup.cfg
harold/project/setup.py_tmpl
harold/project/+package+/__init__.py
harold/project/+package+/controllers/__init__.py
harold/project/+package+/defaults/__init__.py
harold/project/+package+/defaults/functions.kid
harold/project/+package+/layouts/__init__.py
harold/project/+package+/layouts/type_a.kid
harold/project/+package+/layouts/type_b.kid
harold/project/+package+/layouts/type_c.kid
harold/project/+package+/layouts/type_d.kid
harold/project/+package+/layouts/type_e.kid
harold/project/+package+/layouts/type_f.kid
harold/project/+package+/models/__init__.py
harold/project/+package+/models/activemapper_example.py
harold/project/+package+/models/dbapi_example.py
